media_tagging/__init__.py
media_tagging/exceptions.py
media_tagging/media.py
media_tagging/media_tagging_service.py
media_tagging/repositories.py
media_tagging/tagging_result.py
media_tagging/telemetry.py
media_tagging/entrypoints/__init__.py
media_tagging/entrypoints/cli.py
media_tagging/entrypoints/server.py
media_tagging/entrypoints/tracer.py
media_tagging/entrypoints/utils.py
media_tagging/loaders/__init__.py
media_tagging/loaders/base.py
media_tagging/loaders/file.py
media_tagging/loaders/media_loader_service.py
media_tagging/loaders/entrypoints/__init__.py
media_tagging/loaders/entrypoints/cli.py
media_tagging/taggers/__init__.py
media_tagging/taggers/base.py
media_tagging/taggers/fake/__init__.py
media_tagging/taggers/fake/tagger.py
media_tagging/taggers/fake/tagging_strategies.py
media_tagging/taggers/google_cloud/__init__.py
media_tagging/taggers/google_cloud/tagger.py
media_tagging/taggers/google_cloud/tagging_strategies.py
media_tagging/taggers/llm/__init__.py
media_tagging/taggers/llm/utils.py
media_tagging/taggers/llm/gemini/__init__.py
media_tagging/taggers/llm/gemini/tagger.py
media_tagging/taggers/llm/gemini/tagging_strategies.py
media_tagging/taggers/llm/prompts/__init__.py
media_tagging/taggers/llm/prompts/description.txt
media_tagging/taggers/llm/prompts/system.txt
media_tagging/taggers/llm/prompts/tag.txt
media_tagging-2.4.1.dist-info/licenses/LICENSE.txt
media_tagging-2.4.1.dist-info/METADATA
media_tagging-2.4.1.dist-info/WHEEL
media_tagging-2.4.1.dist-info/entry_points.txt
media_tagging-2.4.1.dist-info/top_level.txt
media_tagging-2.4.1.dist-info/RECORD
