Metadata-Version: 2.4
Name: media-tagging
Version: 2.4.1
Summary: Performs tagging of image and videos based on various taggers
Author-email: Andrei Markin <amarkin@google.com>, Sergei Dorogin <segy@google.com>, "Google Inc. (gTech gPS CSE team)" <no-reply@google.com>
License: Apache 2.0
Classifier: Programming Language :: Python :: 3 :: Only
Classifier: Programming Language :: Python :: 3.10
Classifier: Programming Language :: Python :: 3.11
Classifier: Programming Language :: Python :: 3.12
Classifier: Programming Language :: Python :: 3.13
Classifier: Intended Audience :: Developers
Classifier: Topic :: Software Development :: Libraries :: Python Modules
Classifier: Operating System :: OS Independent
Classifier: License :: OSI Approved :: Apache Software License
Requires-Python: >=3.10
License-File: LICENSE.txt
Requires-Dist: pillow
Requires-Dist: smart_open
Requires-Dist: jq
Requires-Dist: garf-executors>=1.0.0
Requires-Dist: garf-io>=1.0.0
Requires-Dist: pandas
Requires-Dist: pydantic
Requires-Dist: SQLalchemy>=2.0.0
Requires-Dist: tenacity
Requires-Dist: google-genai
Requires-Dist: typer
Requires-Dist: opentelemetry-api
Requires-Dist: opentelemetry-sdk
Requires-Dist: opentelemetry-exporter-otlp
Provides-Extra: google-cloud-vision
Requires-Dist: google-cloud-vision==3.9.0; extra == "google-cloud-vision"
Provides-Extra: google-cloud-videointelligence
Requires-Dist: google-cloud-videointelligence==2.15.0; extra == "google-cloud-videointelligence"
Provides-Extra: google-cloud
Requires-Dist: media-tagging[google-cloud-videointelligence,google-cloud-vision]; extra == "google-cloud"
Provides-Extra: server
Requires-Dist: fastapi; extra == "server"
Requires-Dist: pydantic-settings; extra == "server"
Provides-Extra: all
Requires-Dist: media-tagging[google-cloud,server]; extra == "all"
Dynamic: license-file
